[
null,
{"id":1,"expanded":false,"name":"ゲームスタート","order":4,"parentId":0,"scrollX":480,"scrollY":341.5},
{"id":2,"expanded":false,"name":"朝 美咲の家","order":16,"parentId":0,"scrollX":480,"scrollY":341.5},
{"id":3,"expanded":true,"name":"朝 玄関","order":17,"parentId":2,"scrollX":480,"scrollY":342},
{"id":4,"expanded":false,"name":"8月2日","order":6,"parentId":1,"scrollX":480,"scrollY":341},
{"id":5,"expanded":true,"name":"朝 居間","order":18,"parentId":2,"scrollX":480,"scrollY":342},
{"id":6,"expanded":true,"name":"朝 庭","order":19,"parentId":2,"scrollX":547,"scrollY":415.5},
{"id":7,"expanded":true,"name":"朝 お風呂","order":20,"parentId":2,"scrollX":832,"scrollY":640},
{"id":8,"expanded":true,"name":"朝 美咲の部屋","order":21,"parentId":2,"scrollX":480,"scrollY":341},
{"id":9,"expanded":false,"name":"夜 美咲の家","order":25,"parentId":0,"scrollX":832,"scrollY":640},
{"id":10,"expanded":true,"name":"夜 玄関","order":26,"parentId":9,"scrollX":832,"scrollY":640},
{"id":11,"expanded":true,"name":"夜 居間","order":27,"parentId":9,"scrollX":480,"scrollY":342.5},
{"id":12,"expanded":true,"name":"夜 庭","order":28,"parentId":9,"scrollX":832,"scrollY":640},
{"id":13,"expanded":true,"name":"夜 お風呂","order":29,"parentId":9,"scrollX":521,"scrollY":415.5},
{"id":14,"expanded":true,"name":"夜 美咲の部屋","order":30,"parentId":9,"scrollX":832,"scrollY":640},
null,
{"id":16,"expanded":false,"name":"朝 駄菓子屋方面","order":34,"parentId":0,"scrollX":832,"scrollY":640},
{"id":17,"expanded":false,"name":"美咲の家","order":7,"parentId":4,"scrollX":480,"scrollY":358},
{"id":18,"expanded":true,"name":"玄関","order":8,"parentId":17,"scrollX":480,"scrollY":342},
{"id":19,"expanded":true,"name":"居間 夜","order":10,"parentId":17,"scrollX":547,"scrollY":415.5},
{"id":20,"expanded":true,"name":"神社 2","order":89,"parentId":44,"scrollX":480,"scrollY":341.5},
{"id":21,"expanded":true,"name":"美咲の部屋","order":9,"parentId":17,"scrollX":480,"scrollY":342.5},
{"id":22,"expanded":true,"name":"神社 3","order":90,"parentId":44,"scrollX":480,"scrollY":341.5},
{"id":23,"expanded":false,"name":"駄菓子屋方面","order":13,"parentId":4,"scrollX":480,"scrollY":357.5},
{"id":24,"expanded":true,"name":"駄菓子屋外","order":14,"parentId":23,"scrollX":832,"scrollY":640},
{"id":25,"expanded":true,"name":"空き地方面","order":15,"parentId":4,"scrollX":480,"scrollY":341.5},
{"id":26,"expanded":false,"name":"朝 空き地方面","order":50,"parentId":0,"scrollX":832,"scrollY":640},
{"id":27,"expanded":true,"name":"玄関 夜","order":11,"parentId":17,"scrollX":832,"scrollY":640},
{"id":28,"expanded":true,"name":"美咲の部屋 夜","order":12,"parentId":17,"scrollX":480,"scrollY":342},
{"id":29,"expanded":true,"name":"朝 高台 お墓","order":96,"parentId":95,"scrollX":480,"scrollY":341.5},
{"id":30,"expanded":false,"name":"朝 駄菓子屋外","order":35,"parentId":16,"scrollX":832,"scrollY":640},
{"id":31,"expanded":true,"name":"朝 駄菓子屋","order":37,"parentId":16,"scrollX":832,"scrollY":640},
{"id":32,"expanded":true,"name":"朝 空き地","order":51,"parentId":26,"scrollX":832,"scrollY":640},
{"id":33,"expanded":false,"name":"朝 姉妹の家","order":62,"parentId":0,"scrollX":832,"scrollY":640},
{"id":34,"expanded":false,"name":"朝 空き地奥","order":52,"parentId":26,"scrollX":832,"scrollY":640},
{"id":35,"expanded":false,"name":"小梅メイン1","order":104,"parentId":124,"scrollX":480,"scrollY":342},
{"id":36,"expanded":false,"name":"小梅 美咲の家","order":106,"parentId":35,"scrollX":832,"scrollY":640},
{"id":37,"expanded":true,"name":"小梅 橋","order":108,"parentId":35,"scrollX":481,"scrollY":432.5},
{"id":38,"expanded":false,"name":"小梅 空き地方面","order":105,"parentId":35,"scrollX":832,"scrollY":640},
{"id":39,"expanded":true,"name":"小梅 庭","order":107,"parentId":35,"scrollX":480,"scrollY":358},
{"id":40,"expanded":true,"name":"小梅 駄菓子屋外","order":109,"parentId":35,"scrollX":481,"scrollY":432.5},
{"id":41,"expanded":true,"name":"小梅 駄菓子屋","order":110,"parentId":35,"scrollX":480,"scrollY":358},
{"id":42,"expanded":false,"name":"イベント用","order":102,"parentId":0,"scrollX":480,"scrollY":342},
{"id":43,"expanded":false,"name":"朝 駅方面","order":78,"parentId":0,"scrollX":832,"scrollY":640},
{"id":44,"expanded":false,"name":"朝 神社方面","order":82,"parentId":0,"scrollX":480,"scrollY":341.5},
{"id":45,"expanded":true,"name":"朝 琴花の部屋","order":65,"parentId":33,"scrollX":832,"scrollY":640},
{"id":46,"expanded":true,"name":"朝 小梅の部屋","order":64,"parentId":33,"scrollX":832,"scrollY":640},
{"id":47,"expanded":true,"name":"小梅 駅方面","order":111,"parentId":35,"scrollX":480,"scrollY":358},
{"id":48,"expanded":true,"name":"参道への道","order":84,"parentId":44,"scrollX":832,"scrollY":640},
{"id":49,"expanded":true,"name":"参道 1","order":85,"parentId":44,"scrollX":547,"scrollY":415.5},
{"id":50,"expanded":true,"name":"参道 2","order":86,"parentId":44,"scrollX":480,"scrollY":358},
{"id":51,"expanded":true,"name":"朝 駄菓子屋外 釣り","order":36,"parentId":30,"scrollX":832,"scrollY":640},
{"id":52,"expanded":true,"name":"8月1日","order":5,"parentId":1,"scrollX":480,"scrollY":357.5},
{"id":53,"expanded":true,"name":"朝 姉妹の居間","order":63,"parentId":33,"scrollX":832,"scrollY":640},
{"id":54,"expanded":true,"name":"朝 駅","order":79,"parentId":43,"scrollX":832,"scrollY":640},
{"id":55,"expanded":true,"name":"朝 葵の部屋","order":38,"parentId":16,"scrollX":832,"scrollY":640},
{"id":56,"expanded":false,"name":"コンビニ外","order":100,"parentId":0,"scrollX":480,"scrollY":341.5},
{"id":57,"expanded":false,"name":"コンビニ","order":101,"parentId":56,"scrollX":832,"scrollY":640},
{"id":58,"expanded":false,"name":"イベントまとめ","order":3,"parentId":0,"scrollX":480,"scrollY":342},
{"id":59,"expanded":true,"name":"参道 3","order":87,"parentId":44,"scrollX":480,"scrollY":358},
{"id":60,"expanded":true,"name":"神社","order":88,"parentId":44,"scrollX":480,"scrollY":341.5},
{"id":61,"expanded":false,"name":"タイトル画面","order":1,"parentId":0,"scrollX":480,"scrollY":342},
{"id":62,"expanded":true,"name":"朝 空き地奥 崖 崩壊後","order":55,"parentId":81,"scrollX":480,"scrollY":341.5},
{"id":63,"expanded":false,"name":"小梅サブ9","order":112,"parentId":124,"scrollX":832,"scrollY":640},
{"id":64,"expanded":false,"name":"千歳","order":151,"parentId":42,"scrollX":480,"scrollY":341.5},
{"id":65,"expanded":true,"name":"美咲の家","order":153,"parentId":156,"scrollX":480,"scrollY":341.5},
{"id":66,"expanded":true,"name":"朝 トイレ","order":22,"parentId":2,"scrollX":832,"scrollY":640},
{"id":67,"expanded":true,"name":"朝 お風呂","order":23,"parentId":2,"scrollX":832,"scrollY":640},
{"id":68,"expanded":true,"name":"夜 お風呂","order":32,"parentId":9,"scrollX":832,"scrollY":640},
{"id":69,"expanded":true,"name":"夜 トイレ","order":31,"parentId":9,"scrollX":832,"scrollY":640},
{"id":70,"expanded":false,"name":"夜 駄菓子屋方面","order":42,"parentId":0,"scrollX":480,"scrollY":341.5},
{"id":71,"expanded":false,"name":"夜 駄菓子屋外","order":43,"parentId":70,"scrollX":832,"scrollY":640},
{"id":72,"expanded":true,"name":"夜 駄菓子屋外 釣り","order":44,"parentId":71,"scrollX":480,"scrollY":358},
{"id":73,"expanded":true,"name":"夜 駄菓子屋","order":45,"parentId":70,"scrollX":832,"scrollY":640},
{"id":74,"expanded":true,"name":"夜 葵の部屋","order":46,"parentId":70,"scrollX":832,"scrollY":640},
{"id":75,"expanded":true,"name":"朝 葵のトイレ","order":39,"parentId":16,"scrollX":832,"scrollY":640},
{"id":76,"expanded":true,"name":"夜 葵のトイレ","order":47,"parentId":70,"scrollX":832,"scrollY":640},
{"id":77,"expanded":false,"name":"夜 空き地方面","order":57,"parentId":0,"scrollX":832,"scrollY":640},
{"id":78,"expanded":true,"name":"夜 空き地","order":58,"parentId":77,"scrollX":832,"scrollY":640},
{"id":79,"expanded":false,"name":"夜 空き地奥","order":59,"parentId":77,"scrollX":832,"scrollY":640},
{"id":80,"expanded":true,"name":"夜 空き地奥 崖","order":61,"parentId":77,"scrollX":480,"scrollY":430},
{"id":81,"expanded":false,"name":"朝 空き地奥 崖","order":54,"parentId":26,"scrollX":832,"scrollY":640},
{"id":82,"expanded":false,"name":"夜 駅方面","order":80,"parentId":0,"scrollX":832,"scrollY":640},
{"id":83,"expanded":true,"name":"夜 駅","order":81,"parentId":82,"scrollX":480,"scrollY":358},
{"id":84,"expanded":true,"name":"夜 神社方面","order":83,"parentId":44,"scrollX":480,"scrollY":358},
{"id":85,"expanded":false,"name":"朝 姉妹の廊下","order":66,"parentId":33,"scrollX":832,"scrollY":640},
{"id":86,"expanded":false,"name":"朝 姉妹のトイレ","order":67,"parentId":33,"scrollX":832,"scrollY":640},
{"id":87,"expanded":false,"name":"朝 姉妹のお風呂","order":68,"parentId":33,"scrollX":832,"scrollY":640},
{"id":88,"expanded":false,"name":"夜 姉妹の家","order":70,"parentId":0,"scrollX":832,"scrollY":640},
{"id":89,"expanded":true,"name":"夜 姉妹の居間","order":71,"parentId":88,"scrollX":481,"scrollY":427.5},
{"id":90,"expanded":true,"name":"夜 小梅の部屋","order":72,"parentId":88,"scrollX":832,"scrollY":640},
{"id":91,"expanded":false,"name":"夜 姉妹の廊下","order":74,"parentId":88,"scrollX":481,"scrollY":427.5},
{"id":92,"expanded":true,"name":"夜 琴花の部屋","order":73,"parentId":88,"scrollX":832,"scrollY":640},
{"id":93,"expanded":false,"name":"夜 姉妹のトイレ","order":75,"parentId":88,"scrollX":832,"scrollY":640},
{"id":94,"expanded":false,"name":"夜 姉妹のお風呂","order":76,"parentId":88,"scrollX":832,"scrollY":640},
{"id":95,"expanded":false,"name":"朝 高台方面","order":92,"parentId":0,"scrollX":480,"scrollY":341},
{"id":96,"expanded":false,"name":"夜 高台方面","order":97,"parentId":0,"scrollX":832,"scrollY":640},
{"id":97,"expanded":false,"name":"朝 高台 空き地","order":93,"parentId":95,"scrollX":832,"scrollY":640},
{"id":98,"expanded":false,"name":"夜 高台 空き地","order":98,"parentId":96,"scrollX":832,"scrollY":640},
{"id":99,"expanded":false,"name":"朝 高台 坂道","order":94,"parentId":95,"scrollX":480,"scrollY":358},
{"id":100,"expanded":false,"name":"夜 高台 坂道","order":99,"parentId":96,"scrollX":480,"scrollY":358},
{"id":101,"expanded":true,"name":"朝 高台 階段","order":95,"parentId":95,"scrollX":832,"scrollY":640},
{"id":102,"expanded":false,"name":"サブイベント","order":163,"parentId":42,"scrollX":480,"scrollY":341.5},
{"id":103,"expanded":false,"name":"むしあみを貰う","order":164,"parentId":102,"scrollX":480,"scrollY":341.5},
{"id":104,"expanded":false,"name":"朝 姉妹の玄関","order":69,"parentId":33,"scrollX":832,"scrollY":640},
{"id":105,"expanded":false,"name":"夜 姉妹の玄関","order":77,"parentId":88,"scrollX":832,"scrollY":640},
{"id":106,"expanded":true,"name":"朝 駄菓子屋 廊下","order":40,"parentId":16,"scrollX":832,"scrollY":640},
{"id":107,"expanded":true,"name":"夜 駄菓子屋 廊下","order":48,"parentId":70,"scrollX":832,"scrollY":640},
{"id":108,"expanded":true,"name":"朝 駄菓子屋外 釣り","order":53,"parentId":34,"scrollX":832,"scrollY":640},
{"id":109,"expanded":true,"name":"朝 駄菓子屋外 釣り","order":60,"parentId":79,"scrollX":480,"scrollY":354},
{"id":110,"expanded":true,"name":"朝 仏間","order":24,"parentId":2,"scrollX":832,"scrollY":640},
{"id":111,"expanded":true,"name":"夜 仏間","order":33,"parentId":9,"scrollX":832,"scrollY":640},
{"id":112,"expanded":true,"name":"朝 駄菓子屋 お風呂","order":41,"parentId":16,"scrollX":832,"scrollY":640},
{"id":113,"expanded":true,"name":"朝 駄菓子屋 お風呂","order":49,"parentId":70,"scrollX":480,"scrollY":354},
{"id":114,"expanded":false,"name":"小梅 空き地 奥 崖","order":113,"parentId":63,"scrollX":832,"scrollY":640},
{"id":115,"expanded":true,"name":"小梅 迷いの森","order":114,"parentId":63,"scrollX":480,"scrollY":342},
{"id":116,"expanded":false,"name":"小梅サブ10","order":115,"parentId":124,"scrollX":480,"scrollY":341.5},
{"id":117,"expanded":true,"name":"小梅 美咲の部屋","order":116,"parentId":116,"scrollX":832,"scrollY":640},
{"id":118,"expanded":true,"name":"小梅 美咲の玄関","order":117,"parentId":116,"scrollX":832,"scrollY":640},
{"id":119,"expanded":true,"name":"小梅 美咲の居間","order":118,"parentId":116,"scrollX":480,"scrollY":341.5},
{"id":120,"expanded":false,"name":"小梅サブ11","order":119,"parentId":124,"scrollX":832,"scrollY":640},
{"id":121,"expanded":true,"name":"小梅 姉妹の家","order":120,"parentId":120,"scrollX":480,"scrollY":341},
{"id":122,"expanded":false,"name":"小梅 姉妹の玄関","order":121,"parentId":120,"scrollX":832,"scrollY":640},
{"id":123,"expanded":true,"name":"小梅 姉妹の居間","order":122,"parentId":120,"scrollX":832,"scrollY":640},
{"id":124,"expanded":false,"name":"小梅","order":103,"parentId":42,"scrollX":480,"scrollY":342},
{"id":125,"expanded":false,"name":"小梅 姉妹の廊下","order":123,"parentId":120,"scrollX":480,"scrollY":354},
{"id":126,"expanded":false,"name":"小梅サブ12","order":124,"parentId":124,"scrollX":480,"scrollY":341.5},
{"id":127,"expanded":true,"name":"小梅 姉妹の家 (夜)","order":125,"parentId":126,"scrollX":480,"scrollY":355.5},
{"id":128,"expanded":true,"name":"小梅 空き地方面 (夜)","order":126,"parentId":126,"scrollX":832,"scrollY":640},
{"id":129,"expanded":true,"name":"小梅 空き地 (夜)","order":127,"parentId":126,"scrollX":480,"scrollY":355.5},
{"id":130,"expanded":true,"name":"小梅 空き地 奥 (夜)","order":128,"parentId":126,"scrollX":480,"scrollY":352},
{"id":131,"expanded":true,"name":"駅方面","order":154,"parentId":156,"scrollX":832,"scrollY":640},
{"id":132,"expanded":false,"name":"タイトル画面 2周目","order":2,"parentId":61,"scrollX":832,"scrollY":640},
{"id":133,"expanded":false,"name":"琴花","order":129,"parentId":42,"scrollX":480,"scrollY":342},
{"id":134,"expanded":false,"name":"琴花サブ11","order":135,"parentId":133,"scrollX":480,"scrollY":342},
{"id":135,"expanded":false,"name":"琴花 美咲の家","order":136,"parentId":134,"scrollX":832,"scrollY":640},
{"id":136,"expanded":false,"name":"琴花 空き地方面","order":137,"parentId":134,"scrollX":832,"scrollY":640},
{"id":137,"expanded":false,"name":"琴花 姉妹の家","order":138,"parentId":134,"scrollX":480,"scrollY":341.5},
{"id":138,"expanded":false,"name":"琴花 姉妹の家 玄関","order":139,"parentId":134,"scrollX":480,"scrollY":341.5},
{"id":139,"expanded":false,"name":"琴花 姉妹の家 廊下","order":140,"parentId":134,"scrollX":480,"scrollY":341.5},
{"id":140,"expanded":false,"name":"琴花サブ9","order":130,"parentId":133,"scrollX":480,"scrollY":341.5},
{"id":141,"expanded":false,"name":"琴花 姉妹の家","order":131,"parentId":140,"scrollX":480,"scrollY":341.5},
{"id":142,"expanded":false,"name":"琴花サブ10","order":132,"parentId":133,"scrollX":480,"scrollY":341.5},
{"id":143,"expanded":false,"name":"琴花 美咲の家","order":133,"parentId":142,"scrollX":832,"scrollY":640},
{"id":144,"expanded":false,"name":"琴花 駅方面","order":134,"parentId":142,"scrollX":480,"scrollY":341.5},
{"id":145,"expanded":false,"name":"葵","order":141,"parentId":42,"scrollX":480,"scrollY":342},
{"id":146,"expanded":false,"name":"葵サブ10","order":142,"parentId":145,"scrollX":480,"scrollY":342},
{"id":147,"expanded":false,"name":"葵 美咲の家","order":143,"parentId":146,"scrollX":832,"scrollY":640},
{"id":148,"expanded":false,"name":"葵 駅方面","order":144,"parentId":146,"scrollX":480,"scrollY":342.5},
{"id":149,"expanded":false,"name":"葵 駅","order":145,"parentId":146,"scrollX":832,"scrollY":640},
{"id":150,"expanded":false,"name":"葵 駄菓子屋方面 橋","order":147,"parentId":146,"scrollX":832,"scrollY":640},
{"id":151,"expanded":false,"name":"葵 駄菓子屋 外","order":148,"parentId":146,"scrollX":832,"scrollY":640},
{"id":152,"expanded":false,"name":"葵 駄菓子屋","order":149,"parentId":146,"scrollX":480,"scrollY":342},
{"id":153,"expanded":false,"name":"葵 駄菓子屋 廊下","order":150,"parentId":146,"scrollX":480,"scrollY":342},
{"id":154,"expanded":false,"name":"葵 駅 電車到着","order":146,"parentId":146,"scrollX":832,"scrollY":640},
{"id":155,"expanded":true,"name":"神社 完成","order":91,"parentId":44,"scrollX":480,"scrollY":341.5},
{"id":156,"expanded":false,"name":"千歳サブ10","order":152,"parentId":64,"scrollX":832,"scrollY":640},
{"id":157,"expanded":true,"name":"橋","order":155,"parentId":156,"scrollX":832,"scrollY":640},
{"id":158,"expanded":true,"name":"駄菓子屋","order":156,"parentId":156,"scrollX":832,"scrollY":640},
{"id":159,"expanded":true,"name":"神社方面","order":157,"parentId":156,"scrollX":832,"scrollY":640},
{"id":160,"expanded":true,"name":"参道への道","order":158,"parentId":156,"scrollX":832,"scrollY":640},
{"id":161,"expanded":true,"name":"参道1","order":159,"parentId":156,"scrollX":832,"scrollY":640},
{"id":162,"expanded":true,"name":"参道2","order":160,"parentId":156,"scrollX":832,"scrollY":640},
{"id":163,"expanded":true,"name":"参道3","order":161,"parentId":156,"scrollX":832,"scrollY":640},
{"id":164,"expanded":true,"name":"神社","order":162,"parentId":156,"scrollX":480,"scrollY":341.5},
{"id":165,"expanded":true,"name":"迷いの森 入り口","order":56,"parentId":26,"scrollX":480,"scrollY":341.5}
]